{
    "AcquisitionNumber": 1,
    "AcquisitionTime": "18:03:50.450000",
    "EchoNumber": 3,
    "EchoTime": 0.04428,
    "ImageComments": "Unaliased_MB3_PE4_LB_SENSE1+",
    "ImageType": [
        "ORIGINAL",
        "PRIMARY",
        "M",
        "MB",
        "TE3",
        "ND",
        "MOSAIC"
    ],
    "ProcedureStepDescription": "Laird_Laird_DIVA",
    "ProtocolName": "func_task-strangerthings_run-6_ses-02",
    "SAR": 0.0916952,
    "SeriesDescription": "func_task-strangerthings_run-6_ses-02",
    "SeriesNumber": 28,
    "ShimSetting": [
        -168,
        -388,
        930,
        456,
        58,
        295,
        95,
        52
    ],
    "SliceTiming": [
        0,
        0.6475,
        1.295,
        0.4625,
        1.11,
        0.2775,
        0.925,
        0.0925,
        0.74,
        1.3875,
        0.555,
        1.2025,
        0.37,
        1.0175,
        0.185,
        0.8325,
        0,
        0.6475,
        1.295,
        0.4625,
        1.11,
        0.2775,
        0.925,
        0.0925,
        0.74,
        1.3875,
        0.555,
        1.2025,
        0.37,
        1.0175,
        0.185,
        0.8325,
        0,
        0.6475,
        1.295,
        0.4625,
        1.11,
        0.2775,
        0.925,
        0.0925,
        0.74,
        1.3875,
        0.555,
        1.2025,
        0.37,
        1.0175,
        0.185,
        0.8325
    ],
    "TxRefAmp": 231.921,
    "WipMemBlock": "79f96da2-5394-4e76-ab51-5e8e764f7881||Sequence: R016 ve11c/master r/e634e98; Dec 19 2017 11:00:25 by eja"
}